imcs/__init__.py
imcs/schema2avu.py
imcs/lib/__init__.py
imcs/lib/avu_functions.py
imcs/lib/shell.py
imcs/lib/verify_functions.py
imcs-0.0.1.dist-info/METADATA
imcs-0.0.1.dist-info/WHEEL
imcs-0.0.1.dist-info/entry_points.txt
imcs-0.0.1.dist-info/licenses/LICENSE.md
imcs-0.0.1.dist-info/RECORD
