Metadata-Version: 2.1
Name: imcs
Version: 0.0.1
Summary: A CLI for adding metadata in JSON format to iRODs objects
Project-URL: Homepage, https://gitlab.rlp.net/hpc/imcs
Project-URL: Bug Tracker, https://gitlab.rlp.net/hpc/imcs/-/issues
Author-email: Timo Wentong Lin <lin@uni-mainz.de>
License-File: LICENSE.md
Classifier: License :: OSI Approved :: Apache Software License
Classifier: Operating System :: OS Independent
Classifier: Programming Language :: Python :: 3
Classifier: Programming Language :: Python :: 3.8
Classifier: Programming Language :: Python :: 3.9
Requires-Python: >=3.7
Requires-Dist: irods-avu-json>=2.1.0
